<?xml version="1.0" encoding="utf-8"?>
<Dependencies>
  <Dependency>
    <ModuleName>Common</ModuleName>
    <VirtualPath>~/Core/Common</VirtualPath>
    <LoaderName>CoreExtensionLoader</LoaderName>
    <References />
  </Dependency>
  <Dependency>
    <ModuleName>Containers</ModuleName>
    <VirtualPath>~/Core/Containers</VirtualPath>
    <LoaderName>CoreExtensionLoader</LoaderName>
    <References />
  </Dependency>
  <Dependency>
    <ModuleName>Contents</ModuleName>
    <VirtualPath>~/Core/Contents</VirtualPath>
    <LoaderName>CoreExtensionLoader</LoaderName>
    <References />
  </Dependency>
  <Dependency>
    <ModuleName>Dashboard</ModuleName>
    <VirtualPath>~/Core/Dashboard</VirtualPath>
    <LoaderName>CoreExtensionLoader</LoaderName>
    <References />
  </Dependency>
  <Dependency>
    <ModuleName>Feeds</ModuleName>
    <VirtualPath>~/Core/Feeds</VirtualPath>
    <LoaderName>CoreExtensionLoader</LoaderName>
    <References />
  </Dependency>
  <Dependency>
    <ModuleName>Lucene</ModuleName>
    <VirtualPath>~/Modules/Lucene/Lucene.csproj</VirtualPath>
    <LoaderName>DynamicExtensionLoader</LoaderName>
    <References>
      <Reference>
        <Name>Lucene.Net</Name>
        <LoaderName>DynamicExtensionLoader</LoaderName>
        <VirtualPath>~/Modules/Lucene/bin/Lucene.Net.dll</VirtualPath>
      </Reference>
    </References>
  </Dependency>
  <Dependency>
    <ModuleName>Markdown</ModuleName>
    <VirtualPath>~/Modules/Markdown/Markdown.csproj</VirtualPath>
    <LoaderName>DynamicExtensionLoader</LoaderName>
    <References>
      <Reference>
        <Name>MarkdownSharp</Name>
        <LoaderName>DynamicExtensionLoader</LoaderName>
        <VirtualPath>~/Modules/Markdown/bin/MarkdownSharp.dll</VirtualPath>
      </Reference>
    </References>
  </Dependency>
  <Dependency>
    <ModuleName>Navigation</ModuleName>
    <VirtualPath>~/Core/Navigation</VirtualPath>
    <LoaderName>CoreExtensionLoader</LoaderName>
    <References />
  </Dependency>
  <Dependency>
    <ModuleName>Orchard.Alias</ModuleName>
    <VirtualPath>~/Modules/Orchard.Alias/Orchard.Alias.csproj</VirtualPath>
    <LoaderName>DynamicExtensionLoader</LoaderName>
    <References />
  </Dependency>
  <Dependency>
    <ModuleName>Orchard.Tokens</ModuleName>
    <VirtualPath>~/Modules/Orchard.Tokens/Orchard.Tokens.csproj</VirtualPath>
    <LoaderName>DynamicExtensionLoader</LoaderName>
    <References />
  </Dependency>
  <Dependency>
    <ModuleName>Orchard.AntiSpam</ModuleName>
    <VirtualPath>~/Modules/Orchard.AntiSpam/Orchard.AntiSpam.csproj</VirtualPath>
    <LoaderName>DynamicExtensionLoader</LoaderName>
    <References>
      <Reference>
        <Name>Orchard.Tokens</Name>
        <LoaderName>DynamicExtensionLoader</LoaderName>
        <VirtualPath>~/Modules/Orchard.Tokens/Orchard.Tokens.csproj</VirtualPath>
      </Reference>
    </References>
  </Dependency>
  <Dependency>
    <ModuleName>Orchard.ArchiveLater</ModuleName>
    <VirtualPath>~/Modules/Orchard.ArchiveLater/Orchard.ArchiveLater.csproj</VirtualPath>
    <LoaderName>DynamicExtensionLoader</LoaderName>
    <References />
  </Dependency>
  <Dependency>
    <ModuleName>Orchard.Autoroute</ModuleName>
    <VirtualPath>~/Modules/Orchard.Autoroute/Orchard.Autoroute.csproj</VirtualPath>
    <LoaderName>DynamicExtensionLoader</LoaderName>
    <References>
      <Reference>
        <Name>Orchard.Alias</Name>
        <LoaderName>DynamicExtensionLoader</LoaderName>
        <VirtualPath>~/Modules/Orchard.Alias/Orchard.Alias.csproj</VirtualPath>
      </Reference>
      <Reference>
        <Name>Orchard.Tokens</Name>
        <LoaderName>DynamicExtensionLoader</LoaderName>
        <VirtualPath>~/Modules/Orchard.Tokens/Orchard.Tokens.csproj</VirtualPath>
      </Reference>
    </References>
  </Dependency>
  <Dependency>
    <ModuleName>Orchard.OutputCache</ModuleName>
    <VirtualPath>~/Modules/Orchard.OutputCache/Orchard.OutputCache.csproj</VirtualPath>
    <LoaderName>DynamicExtensionLoader</LoaderName>
    <References />
  </Dependency>
  <Dependency>
    <ModuleName>Orchard.Azure</ModuleName>
    <VirtualPath>~/Modules/Orchard.Azure/Orchard.Azure.csproj</VirtualPath>
    <LoaderName>DynamicExtensionLoader</LoaderName>
    <References>
      <Reference>
        <Name>Microsoft.ApplicationServer.Caching.AzureClientHelper</Name>
        <LoaderName>DynamicExtensionLoader</LoaderName>
        <VirtualPath>~/Modules/Orchard.Azure/bin/Microsoft.ApplicationServer.Caching.AzureClientHelper.dll</VirtualPath>
      </Reference>
      <Reference>
        <Name>Microsoft.ApplicationServer.Caching.Client</Name>
        <LoaderName>DynamicExtensionLoader</LoaderName>
        <VirtualPath>~/Modules/Orchard.Azure/bin/Microsoft.ApplicationServer.Caching.Client.dll</VirtualPath>
      </Reference>
      <Reference>
        <Name>Microsoft.ApplicationServer.Caching.Core</Name>
        <LoaderName>DynamicExtensionLoader</LoaderName>
        <VirtualPath>~/Modules/Orchard.Azure/bin/Microsoft.ApplicationServer.Caching.Core.dll</VirtualPath>
      </Reference>
      <Reference>
        <Name>Microsoft.WindowsAzure.Configuration</Name>
        <LoaderName>DynamicExtensionLoader</LoaderName>
        <VirtualPath>~/Modules/Orchard.Azure/bin/Microsoft.WindowsAzure.Configuration.dll</VirtualPath>
      </Reference>
      <Reference>
        <Name>Microsoft.WindowsAzure.Diagnostics.StorageUtility</Name>
        <LoaderName>DynamicExtensionLoader</LoaderName>
        <VirtualPath>~/Modules/Orchard.Azure/bin/Microsoft.WindowsAzure.Diagnostics.StorageUtility.dll</VirtualPath>
      </Reference>
      <Reference>
        <Name>Microsoft.WindowsAzure.Storage</Name>
        <LoaderName>DynamicExtensionLoader</LoaderName>
        <VirtualPath>~/Modules/Orchard.Azure/bin/Microsoft.WindowsAzure.Storage.dll</VirtualPath>
      </Reference>
      <Reference>
        <Name>Orchard.OutputCache</Name>
        <LoaderName>DynamicExtensionLoader</LoaderName>
        <VirtualPath>~/Modules/Orchard.OutputCache/Orchard.OutputCache.csproj</VirtualPath>
      </Reference>
    </References>
  </Dependency>
  <Dependency>
    <ModuleName>Orchard.ContentPicker</ModuleName>
    <VirtualPath>~/Modules/Orchard.ContentPicker/Orchard.ContentPicker.csproj</VirtualPath>
    <LoaderName>DynamicExtensionLoader</LoaderName>
    <References />
  </Dependency>
  <Dependency>
    <ModuleName>Orchard.Blogs</ModuleName>
    <VirtualPath>~/Modules/Orchard.Blogs/Orchard.Blogs.csproj</VirtualPath>
    <LoaderName>DynamicExtensionLoader</LoaderName>
    <References>
      <Reference>
        <Name>Orchard.ContentPicker</Name>
        <LoaderName>DynamicExtensionLoader</LoaderName>
        <VirtualPath>~/Modules/Orchard.ContentPicker/Orchard.ContentPicker.csproj</VirtualPath>
      </Reference>
    </References>
  </Dependency>
  <Dependency>
    <ModuleName>Orchard.CodeGeneration</ModuleName>
    <VirtualPath>~/Modules/Orchard.CodeGeneration/Orchard.CodeGeneration.csproj</VirtualPath>
    <LoaderName>DynamicExtensionLoader</LoaderName>
    <References />
  </Dependency>
  <Dependency>
    <ModuleName>Orchard.Forms</ModuleName>
    <VirtualPath>~/Modules/Orchard.Forms/Orchard.Forms.csproj</VirtualPath>
    <LoaderName>DynamicExtensionLoader</LoaderName>
    <References />
  </Dependency>
  <Dependency>
    <ModuleName>Orchard.Workflows</ModuleName>
    <VirtualPath>~/Modules/Orchard.Workflows/Orchard.Workflows.csproj</VirtualPath>
    <LoaderName>DynamicExtensionLoader</LoaderName>
    <References>
      <Reference>
        <Name>Orchard.Forms</Name>
        <LoaderName>DynamicExtensionLoader</LoaderName>
        <VirtualPath>~/Modules/Orchard.Forms/Orchard.Forms.csproj</VirtualPath>
      </Reference>
      <Reference>
        <Name>Orchard.Tokens</Name>
        <LoaderName>DynamicExtensionLoader</LoaderName>
        <VirtualPath>~/Modules/Orchard.Tokens/Orchard.Tokens.csproj</VirtualPath>
      </Reference>
    </References>
  </Dependency>
  <Dependency>
    <ModuleName>Orchard.Comments</ModuleName>
    <VirtualPath>~/Modules/Orchard.Comments/Orchard.Comments.csproj</VirtualPath>
    <LoaderName>DynamicExtensionLoader</LoaderName>
    <References>
      <Reference>
        <Name>Orchard.Tokens</Name>
        <LoaderName>DynamicExtensionLoader</LoaderName>
        <VirtualPath>~/Modules/Orchard.Tokens/Orchard.Tokens.csproj</VirtualPath>
      </Reference>
      <Reference>
        <Name>Orchard.Workflows</Name>
        <LoaderName>DynamicExtensionLoader</LoaderName>
        <VirtualPath>~/Modules/Orchard.Workflows/Orchard.Workflows.csproj</VirtualPath>
      </Reference>
    </References>
  </Dependency>
  <Dependency>
    <ModuleName>Orchard.Roles</ModuleName>
    <VirtualPath>~/Modules/Orchard.Roles/Orchard.Roles.csproj</VirtualPath>
    <LoaderName>DynamicExtensionLoader</LoaderName>
    <References>
      <Reference>
        <Name>Orchard.Forms</Name>
        <LoaderName>DynamicExtensionLoader</LoaderName>
        <VirtualPath>~/Modules/Orchard.Forms/Orchard.Forms.csproj</VirtualPath>
      </Reference>
      <Reference>
        <Name>Orchard.Workflows</Name>
        <LoaderName>DynamicExtensionLoader</LoaderName>
        <VirtualPath>~/Modules/Orchard.Workflows/Orchard.Workflows.csproj</VirtualPath>
      </Reference>
    </References>
  </Dependency>
  <Dependency>
    <ModuleName>Orchard.ContentPermissions</ModuleName>
    <VirtualPath>~/Modules/Orchard.ContentPermissions/Orchard.ContentPermissions.csproj</VirtualPath>
    <LoaderName>DynamicExtensionLoader</LoaderName>
    <References>
      <Reference>
        <Name>Orchard.Roles</Name>
        <LoaderName>DynamicExtensionLoader</LoaderName>
        <VirtualPath>~/Modules/Orchard.Roles/Orchard.Roles.csproj</VirtualPath>
      </Reference>
    </References>
  </Dependency>
  <Dependency>
    <ModuleName>Orchard.Themes</ModuleName>
    <VirtualPath>~/Modules/Orchard.Themes/Orchard.Themes.csproj</VirtualPath>
    <LoaderName>DynamicExtensionLoader</LoaderName>
    <References />
  </Dependency>
  <Dependency>
    <ModuleName>Orchard.ContentTypes</ModuleName>
    <VirtualPath>~/Modules/Orchard.ContentTypes/Orchard.ContentTypes.csproj</VirtualPath>
    <LoaderName>DynamicExtensionLoader</LoaderName>
    <References>
      <Reference>
        <Name>Orchard.Themes</Name>
        <LoaderName>DynamicExtensionLoader</LoaderName>
        <VirtualPath>~/Modules/Orchard.Themes/Orchard.Themes.csproj</VirtualPath>
      </Reference>
    </References>
  </Dependency>
  <Dependency>
    <ModuleName>Orchard.CustomForms</ModuleName>
    <VirtualPath>~/Modules/Orchard.CustomForms/Orchard.CustomForms.csproj</VirtualPath>
    <LoaderName>DynamicExtensionLoader</LoaderName>
    <References>
      <Reference>
        <Name>Orchard.Forms</Name>
        <LoaderName>DynamicExtensionLoader</LoaderName>
        <VirtualPath>~/Modules/Orchard.Forms/Orchard.Forms.csproj</VirtualPath>
      </Reference>
      <Reference>
        <Name>Orchard.Tokens</Name>
        <LoaderName>DynamicExtensionLoader</LoaderName>
        <VirtualPath>~/Modules/Orchard.Tokens/Orchard.Tokens.csproj</VirtualPath>
      </Reference>
      <Reference>
        <Name>Orchard.Workflows</Name>
        <LoaderName>DynamicExtensionLoader</LoaderName>
        <VirtualPath>~/Modules/Orchard.Workflows/Orchard.Workflows.csproj</VirtualPath>
      </Reference>
    </References>
  </Dependency>
  <Dependency>
    <ModuleName>Orchard.Scripting</ModuleName>
    <VirtualPath>~/Modules/Orchard.Scripting/Orchard.Scripting.csproj</VirtualPath>
    <LoaderName>DynamicExtensionLoader</LoaderName>
    <References />
  </Dependency>
  <Dependency>
    <ModuleName>Orchard.Widgets</ModuleName>
    <VirtualPath>~/Modules/Orchard.Widgets/Orchard.Widgets.csproj</VirtualPath>
    <LoaderName>DynamicExtensionLoader</LoaderName>
    <References>
      <Reference>
        <Name>Orchard.Scripting</Name>
        <LoaderName>DynamicExtensionLoader</LoaderName>
        <VirtualPath>~/Modules/Orchard.Scripting/Orchard.Scripting.csproj</VirtualPath>
      </Reference>
      <Reference>
        <Name>Orchard.Themes</Name>
        <LoaderName>DynamicExtensionLoader</LoaderName>
        <VirtualPath>~/Modules/Orchard.Themes/Orchard.Themes.csproj</VirtualPath>
      </Reference>
    </References>
  </Dependency>
  <Dependency>
    <ModuleName>Orchard.DesignerTools</ModuleName>
    <VirtualPath>~/Modules/Orchard.DesignerTools/Orchard.DesignerTools.csproj</VirtualPath>
    <LoaderName>DynamicExtensionLoader</LoaderName>
    <References>
      <Reference>
        <Name>Orchard.Widgets</Name>
        <LoaderName>DynamicExtensionLoader</LoaderName>
        <VirtualPath>~/Modules/Orchard.Widgets/Orchard.Widgets.csproj</VirtualPath>
      </Reference>
    </References>
  </Dependency>
  <Dependency>
    <ModuleName>Orchard.Email</ModuleName>
    <VirtualPath>~/Modules/Orchard.Email/Orchard.Email.csproj</VirtualPath>
    <LoaderName>DynamicExtensionLoader</LoaderName>
    <References>
      <Reference>
        <Name>Orchard.Forms</Name>
        <LoaderName>DynamicExtensionLoader</LoaderName>
        <VirtualPath>~/Modules/Orchard.Forms/Orchard.Forms.csproj</VirtualPath>
      </Reference>
      <Reference>
        <Name>Orchard.Workflows</Name>
        <LoaderName>DynamicExtensionLoader</LoaderName>
        <VirtualPath>~/Modules/Orchard.Workflows/Orchard.Workflows.csproj</VirtualPath>
      </Reference>
    </References>
  </Dependency>
  <Dependency>
    <ModuleName>Orchard.Media</ModuleName>
    <VirtualPath>~/Modules/Orchard.Media/Orchard.Media.csproj</VirtualPath>
    <LoaderName>DynamicExtensionLoader</LoaderName>
    <References>
      <Reference>
        <Name>Ionic.Zip</Name>
        <LoaderName>DynamicExtensionLoader</LoaderName>
        <VirtualPath>~/Modules/Orchard.Media/bin/Ionic.Zip.dll</VirtualPath>
      </Reference>
    </References>
  </Dependency>
  <Dependency>
    <ModuleName>Orchard.Fields</ModuleName>
    <VirtualPath>~/Modules/Orchard.Fields/Orchard.Fields.csproj</VirtualPath>
    <LoaderName>DynamicExtensionLoader</LoaderName>
    <References>
      <Reference>
        <Name>Orchard.Media</Name>
        <LoaderName>DynamicExtensionLoader</LoaderName>
        <VirtualPath>~/Modules/Orchard.Media/Orchard.Media.csproj</VirtualPath>
      </Reference>
    </References>
  </Dependency>
  <Dependency>
    <ModuleName>Orchard.MediaLibrary</ModuleName>
    <VirtualPath>~/Modules/Orchard.MediaLibrary/Orchard.MediaLibrary.csproj</VirtualPath>
    <LoaderName>DynamicExtensionLoader</LoaderName>
    <References>
      <Reference>
        <Name>Orchard.Tokens</Name>
        <LoaderName>DynamicExtensionLoader</LoaderName>
        <VirtualPath>~/Modules/Orchard.Tokens/Orchard.Tokens.csproj</VirtualPath>
      </Reference>
    </References>
  </Dependency>
  <Dependency>
    <ModuleName>Orchard.ImageEditor</ModuleName>
    <VirtualPath>~/Modules/Orchard.ImageEditor/Orchard.ImageEditor.csproj</VirtualPath>
    <LoaderName>DynamicExtensionLoader</LoaderName>
    <References>
      <Reference>
        <Name>Orchard.MediaLibrary</Name>
        <LoaderName>DynamicExtensionLoader</LoaderName>
        <VirtualPath>~/Modules/Orchard.MediaLibrary/Orchard.MediaLibrary.csproj</VirtualPath>
      </Reference>
    </References>
  </Dependency>
  <Dependency>
    <ModuleName>Orchard.ImportExport</ModuleName>
    <VirtualPath>~/Modules/Orchard.ImportExport/Orchard.ImportExport.csproj</VirtualPath>
    <LoaderName>DynamicExtensionLoader</LoaderName>
    <References />
  </Dependency>
  <Dependency>
    <ModuleName>Orchard.Indexing</ModuleName>
    <VirtualPath>~/Modules/Orchard.Indexing/Orchard.Indexing.csproj</VirtualPath>
    <LoaderName>DynamicExtensionLoader</LoaderName>
    <References />
  </Dependency>
  <Dependency>
    <ModuleName>Orchard.jQuery</ModuleName>
    <VirtualPath>~/Modules/Orchard.jQuery/Orchard.jQuery.csproj</VirtualPath>
    <LoaderName>DynamicExtensionLoader</LoaderName>
    <References />
  </Dependency>
  <Dependency>
    <ModuleName>Orchard.Lists</ModuleName>
    <VirtualPath>~/Modules/Orchard.Lists/Orchard.Lists.csproj</VirtualPath>
    <LoaderName>DynamicExtensionLoader</LoaderName>
    <References />
  </Dependency>
  <Dependency>
    <ModuleName>Orchard.Localization</ModuleName>
    <VirtualPath>~/Modules/Orchard.Localization/Orchard.Localization.csproj</VirtualPath>
    <LoaderName>DynamicExtensionLoader</LoaderName>
    <References />
  </Dependency>
  <Dependency>
    <ModuleName>Orchard.MediaPicker</ModuleName>
    <VirtualPath>~/Modules/Orchard.MediaPicker/Orchard.MediaPicker.csproj</VirtualPath>
    <LoaderName>DynamicExtensionLoader</LoaderName>
    <References>
      <Reference>
        <Name>Orchard.Media</Name>
        <LoaderName>DynamicExtensionLoader</LoaderName>
        <VirtualPath>~/Modules/Orchard.Media/Orchard.Media.csproj</VirtualPath>
      </Reference>
    </References>
  </Dependency>
  <Dependency>
    <ModuleName>Orchard.MediaProcessing</ModuleName>
    <VirtualPath>~/Modules/Orchard.MediaProcessing/Orchard.MediaProcessing.csproj</VirtualPath>
    <LoaderName>DynamicExtensionLoader</LoaderName>
    <References>
      <Reference>
        <Name>ImageResizer</Name>
        <LoaderName>DynamicExtensionLoader</LoaderName>
        <VirtualPath>~/Modules/Orchard.MediaProcessing/bin/ImageResizer.dll</VirtualPath>
      </Reference>
      <Reference>
        <Name>Orchard.Forms</Name>
        <LoaderName>DynamicExtensionLoader</LoaderName>
        <VirtualPath>~/Modules/Orchard.Forms/Orchard.Forms.csproj</VirtualPath>
      </Reference>
      <Reference>
        <Name>Orchard.Tokens</Name>
        <LoaderName>DynamicExtensionLoader</LoaderName>
        <VirtualPath>~/Modules/Orchard.Tokens/Orchard.Tokens.csproj</VirtualPath>
      </Reference>
    </References>
  </Dependency>
  <Dependency>
    <ModuleName>Orchard.Messaging</ModuleName>
    <VirtualPath>~/Modules/Orchard.Messaging/Orchard.Messaging.csproj</VirtualPath>
    <LoaderName>DynamicExtensionLoader</LoaderName>
    <References />
  </Dependency>
  <Dependency>
    <ModuleName>Orchard.Migrations</ModuleName>
    <VirtualPath>~/Modules/Orchard.Migrations/Orchard.Migrations.csproj</VirtualPath>
    <LoaderName>DynamicExtensionLoader</LoaderName>
    <References />
  </Dependency>
  <Dependency>
    <ModuleName>Orchard.Modules</ModuleName>
    <VirtualPath>~/Modules/Orchard.Modules/bin/Orchard.Modules.dll</VirtualPath>
    <LoaderName>PrecompiledExtensionLoader</LoaderName>
    <References />
  </Dependency>
  <Dependency>
    <ModuleName>Orchard.MultiTenancy</ModuleName>
    <VirtualPath>~/Modules/Orchard.MultiTenancy/Orchard.MultiTenancy.csproj</VirtualPath>
    <LoaderName>DynamicExtensionLoader</LoaderName>
    <References />
  </Dependency>
  <Dependency>
    <ModuleName>Orchard.Packaging</ModuleName>
    <VirtualPath>~/Modules/Orchard.Packaging/bin/Orchard.Packaging.dll</VirtualPath>
    <LoaderName>PrecompiledExtensionLoader</LoaderName>
    <References>
      <Reference>
        <Name>Orchard.Modules</Name>
        <LoaderName>PrecompiledExtensionLoader</LoaderName>
        <VirtualPath>~/Modules/Orchard.Modules/bin/Orchard.Modules.dll</VirtualPath>
      </Reference>
    </References>
  </Dependency>
  <Dependency>
    <ModuleName>Orchard.Pages</ModuleName>
    <VirtualPath>~/Modules/Orchard.Pages/Orchard.Pages.csproj</VirtualPath>
    <LoaderName>DynamicExtensionLoader</LoaderName>
    <References>
      <Reference>
        <Name>Orchard.ContentPicker</Name>
        <LoaderName>DynamicExtensionLoader</LoaderName>
        <VirtualPath>~/Modules/Orchard.ContentPicker/Orchard.ContentPicker.csproj</VirtualPath>
      </Reference>
    </References>
  </Dependency>
  <Dependency>
    <ModuleName>Orchard.Projections</ModuleName>
    <VirtualPath>~/Modules/Orchard.Projections/Orchard.Projections.csproj</VirtualPath>
    <LoaderName>DynamicExtensionLoader</LoaderName>
    <References>
      <Reference>
        <Name>Orchard.Forms</Name>
        <LoaderName>DynamicExtensionLoader</LoaderName>
        <VirtualPath>~/Modules/Orchard.Forms/Orchard.Forms.csproj</VirtualPath>
      </Reference>
      <Reference>
        <Name>Orchard.Tokens</Name>
        <LoaderName>DynamicExtensionLoader</LoaderName>
        <VirtualPath>~/Modules/Orchard.Tokens/Orchard.Tokens.csproj</VirtualPath>
      </Reference>
    </References>
  </Dependency>
  <Dependency>
    <ModuleName>Orchard.PublishLater</ModuleName>
    <VirtualPath>~/Modules/Orchard.PublishLater/Orchard.PublishLater.csproj</VirtualPath>
    <LoaderName>DynamicExtensionLoader</LoaderName>
    <References />
  </Dependency>
  <Dependency>
    <ModuleName>Orchard.Recipes</ModuleName>
    <VirtualPath>~/Modules/Orchard.Recipes/Orchard.Recipes.csproj</VirtualPath>
    <LoaderName>DynamicExtensionLoader</LoaderName>
    <References>
      <Reference>
        <Name>Orchard.Packaging</Name>
        <LoaderName>PrecompiledExtensionLoader</LoaderName>
        <VirtualPath>~/Modules/Orchard.Packaging/bin/Orchard.Packaging.dll</VirtualPath>
      </Reference>
      <Reference>
        <Name>Orchard.Themes</Name>
        <LoaderName>DynamicExtensionLoader</LoaderName>
        <VirtualPath>~/Modules/Orchard.Themes/Orchard.Themes.csproj</VirtualPath>
      </Reference>
    </References>
  </Dependency>
  <Dependency>
    <ModuleName>Orchard.Rules</ModuleName>
    <VirtualPath>~/Modules/Orchard.Rules/Orchard.Rules.csproj</VirtualPath>
    <LoaderName>DynamicExtensionLoader</LoaderName>
    <References>
      <Reference>
        <Name>Orchard.Forms</Name>
        <LoaderName>DynamicExtensionLoader</LoaderName>
        <VirtualPath>~/Modules/Orchard.Forms/Orchard.Forms.csproj</VirtualPath>
      </Reference>
      <Reference>
        <Name>Orchard.Scripting</Name>
        <LoaderName>DynamicExtensionLoader</LoaderName>
        <VirtualPath>~/Modules/Orchard.Scripting/Orchard.Scripting.csproj</VirtualPath>
      </Reference>
      <Reference>
        <Name>Orchard.Tokens</Name>
        <LoaderName>DynamicExtensionLoader</LoaderName>
        <VirtualPath>~/Modules/Orchard.Tokens/Orchard.Tokens.csproj</VirtualPath>
      </Reference>
    </References>
  </Dependency>
  <Dependency>
    <ModuleName>Orchard.Scripting.CSharp</ModuleName>
    <VirtualPath>~/Modules/Orchard.Scripting.CSharp/Orchard.Scripting.CSharp.csproj</VirtualPath>
    <LoaderName>DynamicExtensionLoader</LoaderName>
    <References>
      <Reference>
        <Name>Mono.CSharp</Name>
        <LoaderName>DynamicExtensionLoader</LoaderName>
        <VirtualPath>~/Modules/Orchard.Scripting.CSharp/Lib/Mono.CSharp.dll</VirtualPath>
      </Reference>
      <Reference>
        <Name>Orchard.Forms</Name>
        <LoaderName>DynamicExtensionLoader</LoaderName>
        <VirtualPath>~/Modules/Orchard.Forms/Orchard.Forms.csproj</VirtualPath>
      </Reference>
      <Reference>
        <Name>Orchard.Workflows</Name>
        <LoaderName>DynamicExtensionLoader</LoaderName>
        <VirtualPath>~/Modules/Orchard.Workflows/Orchard.Workflows.csproj</VirtualPath>
      </Reference>
    </References>
  </Dependency>
  <Dependency>
    <ModuleName>Orchard.Scripting.Dlr</ModuleName>
    <VirtualPath>~/Modules/Orchard.Scripting.Dlr/Orchard.Scripting.Dlr.csproj</VirtualPath>
    <LoaderName>DynamicExtensionLoader</LoaderName>
    <References>
      <Reference>
        <Name>IronRuby</Name>
        <LoaderName>DynamicExtensionLoader</LoaderName>
        <VirtualPath>~/Modules/Orchard.Scripting.Dlr/bin/IronRuby.dll</VirtualPath>
      </Reference>
      <Reference>
        <Name>IronRuby.Libraries</Name>
        <LoaderName>DynamicExtensionLoader</LoaderName>
        <VirtualPath>~/Modules/Orchard.Scripting.Dlr/bin/IronRuby.Libraries.dll</VirtualPath>
      </Reference>
      <Reference>
        <Name>Microsoft.Dynamic</Name>
        <LoaderName>DynamicExtensionLoader</LoaderName>
        <VirtualPath>~/Modules/Orchard.Scripting.Dlr/bin/Microsoft.Dynamic.dll</VirtualPath>
      </Reference>
      <Reference>
        <Name>Microsoft.Scripting</Name>
        <LoaderName>DynamicExtensionLoader</LoaderName>
        <VirtualPath>~/Modules/Orchard.Scripting.Dlr/bin/Microsoft.Scripting.dll</VirtualPath>
      </Reference>
      <Reference>
        <Name>Orchard.Scripting</Name>
        <LoaderName>DynamicExtensionLoader</LoaderName>
        <VirtualPath>~/Modules/Orchard.Scripting/Orchard.Scripting.csproj</VirtualPath>
      </Reference>
    </References>
  </Dependency>
  <Dependency>
    <ModuleName>Orchard.Search</ModuleName>
    <VirtualPath>~/Modules/Orchard.Search/Orchard.Search.csproj</VirtualPath>
    <LoaderName>DynamicExtensionLoader</LoaderName>
    <References />
  </Dependency>
  <Dependency>
    <ModuleName>Orchard.Setup</ModuleName>
    <VirtualPath>~/Modules/Orchard.Setup/Orchard.Setup.csproj</VirtualPath>
    <LoaderName>DynamicExtensionLoader</LoaderName>
    <References>
      <Reference>
        <Name>Orchard.Recipes</Name>
        <LoaderName>DynamicExtensionLoader</LoaderName>
        <VirtualPath>~/Modules/Orchard.Recipes/Orchard.Recipes.csproj</VirtualPath>
      </Reference>
      <Reference>
        <Name>Orchard.Themes</Name>
        <LoaderName>DynamicExtensionLoader</LoaderName>
        <VirtualPath>~/Modules/Orchard.Themes/Orchard.Themes.csproj</VirtualPath>
      </Reference>
    </References>
  </Dependency>
  <Dependency>
    <ModuleName>Orchard.Tags</ModuleName>
    <VirtualPath>~/Modules/Orchard.Tags/Orchard.Tags.csproj</VirtualPath>
    <LoaderName>DynamicExtensionLoader</LoaderName>
    <References />
  </Dependency>
  <Dependency>
    <ModuleName>Orchard.TaskLease</ModuleName>
    <VirtualPath>~/Modules/Orchard.TaskLease/Orchard.TaskLease.csproj</VirtualPath>
    <LoaderName>DynamicExtensionLoader</LoaderName>
    <References />
  </Dependency>
  <Dependency>
    <ModuleName>Orchard.Taxonomies</ModuleName>
    <VirtualPath>~/Modules/Orchard.Taxonomies/Orchard.Taxonomies.csproj</VirtualPath>
    <LoaderName>DynamicExtensionLoader</LoaderName>
    <References>
      <Reference>
        <Name>Orchard.Alias</Name>
        <LoaderName>DynamicExtensionLoader</LoaderName>
        <VirtualPath>~/Modules/Orchard.Alias/Orchard.Alias.csproj</VirtualPath>
      </Reference>
      <Reference>
        <Name>Orchard.Autoroute</Name>
        <LoaderName>DynamicExtensionLoader</LoaderName>
        <VirtualPath>~/Modules/Orchard.Autoroute/Orchard.Autoroute.csproj</VirtualPath>
      </Reference>
      <Reference>
        <Name>Orchard.Tokens</Name>
        <LoaderName>DynamicExtensionLoader</LoaderName>
        <VirtualPath>~/Modules/Orchard.Tokens/Orchard.Tokens.csproj</VirtualPath>
      </Reference>
    </References>
  </Dependency>
  <Dependency>
    <ModuleName>Orchard.Users</ModuleName>
    <VirtualPath>~/Modules/Orchard.Users/Orchard.Users.csproj</VirtualPath>
    <LoaderName>DynamicExtensionLoader</LoaderName>
    <References />
  </Dependency>
  <Dependency>
    <ModuleName>Orchard.Warmup</ModuleName>
    <VirtualPath>~/Modules/Orchard.Warmup/Orchard.Warmup.csproj</VirtualPath>
    <LoaderName>DynamicExtensionLoader</LoaderName>
    <References />
  </Dependency>
  <Dependency>
    <ModuleName>Reports</ModuleName>
    <VirtualPath>~/Core/Reports</VirtualPath>
    <LoaderName>CoreExtensionLoader</LoaderName>
    <References />
  </Dependency>
  <Dependency>
    <ModuleName>SafeMode</ModuleName>
    <VirtualPath>~/Theme/SafeMode</VirtualPath>
    <LoaderName>RawThemeExtensionLoader</LoaderName>
    <References />
  </Dependency>
  <Dependency>
    <ModuleName>Scheduling</ModuleName>
    <VirtualPath>~/Core/Scheduling</VirtualPath>
    <LoaderName>CoreExtensionLoader</LoaderName>
    <References />
  </Dependency>
  <Dependency>
    <ModuleName>Settings</ModuleName>
    <VirtualPath>~/Core/Settings</VirtualPath>
    <LoaderName>CoreExtensionLoader</LoaderName>
    <References />
  </Dependency>
  <Dependency>
    <ModuleName>Shapes</ModuleName>
    <VirtualPath>~/Core/Shapes</VirtualPath>
    <LoaderName>CoreExtensionLoader</LoaderName>
    <References />
  </Dependency>
  <Dependency>
    <ModuleName>SysCache</ModuleName>
    <VirtualPath>~/Modules/SysCache/SysCache.csproj</VirtualPath>
    <LoaderName>DynamicExtensionLoader</LoaderName>
    <References>
      <Reference>
        <Name>NHibernate.Caches.SysCache2</Name>
        <LoaderName>DynamicExtensionLoader</LoaderName>
        <VirtualPath>~/Modules/SysCache/bin/NHibernate.Caches.SysCache2.dll</VirtualPath>
      </Reference>
    </References>
  </Dependency>
  <Dependency>
    <ModuleName>TheAdmin</ModuleName>
    <VirtualPath>~/Theme/TheAdmin</VirtualPath>
    <LoaderName>RawThemeExtensionLoader</LoaderName>
    <References />
  </Dependency>
  <Dependency>
    <ModuleName>TheThemeMachine</ModuleName>
    <VirtualPath>~/Theme/TheThemeMachine</VirtualPath>
    <LoaderName>RawThemeExtensionLoader</LoaderName>
    <References />
  </Dependency>
  <Dependency>
    <ModuleName>TinyMce</ModuleName>
    <VirtualPath>~/Modules/TinyMce/TinyMce.csproj</VirtualPath>
    <LoaderName>DynamicExtensionLoader</LoaderName>
    <References />
  </Dependency>
  <Dependency>
    <ModuleName>Title</ModuleName>
    <VirtualPath>~/Core/Title</VirtualPath>
    <LoaderName>CoreExtensionLoader</LoaderName>
    <References />
  </Dependency>
  <Dependency>
    <ModuleName>Upgrade</ModuleName>
    <VirtualPath>~/Modules/Upgrade/Upgrade.csproj</VirtualPath>
    <LoaderName>DynamicExtensionLoader</LoaderName>
    <References>
      <Reference>
        <Name>Orchard.Alias</Name>
        <LoaderName>DynamicExtensionLoader</LoaderName>
        <VirtualPath>~/Modules/Orchard.Alias/Orchard.Alias.csproj</VirtualPath>
      </Reference>
      <Reference>
        <Name>Orchard.Autoroute</Name>
        <LoaderName>DynamicExtensionLoader</LoaderName>
        <VirtualPath>~/Modules/Orchard.Autoroute/Orchard.Autoroute.csproj</VirtualPath>
      </Reference>
      <Reference>
        <Name>Orchard.MediaLibrary</Name>
        <LoaderName>DynamicExtensionLoader</LoaderName>
        <VirtualPath>~/Modules/Orchard.MediaLibrary/Orchard.MediaLibrary.csproj</VirtualPath>
      </Reference>
      <Reference>
        <Name>Orchard.Widgets</Name>
        <LoaderName>DynamicExtensionLoader</LoaderName>
        <VirtualPath>~/Modules/Orchard.Widgets/Orchard.Widgets.csproj</VirtualPath>
      </Reference>
    </References>
  </Dependency>
  <Dependency>
    <ModuleName>XmlRpc</ModuleName>
    <VirtualPath>~/Core/XmlRpc</VirtualPath>
    <LoaderName>CoreExtensionLoader</LoaderName>
    <References />
  </Dependency>
</Dependencies>